colorcode/__init__.py
colorcode/__main__.py
colorcode/cli.py
colorcode/loader.py
colorcode/aztec/encoder.cp37-win_amd64.pyd
colorcode/aztec/reedsolomon/galloisfield.cp37-win_amd64.pyd
colorcode-1.0.2.dist-info/LICENSE
colorcode-1.0.2.dist-info/METADATA
colorcode-1.0.2.dist-info/WHEEL
colorcode-1.0.2.dist-info/entry_points.txt
colorcode-1.0.2.dist-info/top_level.txt
colorcode-1.0.2.dist-info/RECORD
