Metadata-Version: 2.1
Name: colorcode
Version: 1.0.2
Summary: Using Python to make multi-colored 2D codes!
Home-page: https://git.heptacle.fr/neshiraini/colorcode
Author: Nathan/Eilisha Shiraini
Author-email: neshiraini+colorcode@heptacle.fr
License: UNKNOWN
Platform: UNKNOWN
Classifier: Development Status :: 7 - Inactive
Classifier: License :: OSI Approved :: MIT License
Classifier: Programming Language :: C++
Classifier: Programming Language :: Cython
Classifier: Programming Language :: Python :: 3
Classifier: Topic :: Multimedia :: Graphics
Classifier: Topic :: Utilities
Requires-Dist: Cython
Requires-Dist: numpy
Requires-Dist: Pillow
